cli/__init__.py
cli/config_generator.py
cli/consts.py
cli/core.py
cli/docker_cli.py
cli/main.py
cli/targets.py
cli/utils.py
archgw-0.3.22.dist-info/METADATA
archgw-0.3.22.dist-info/WHEEL
archgw-0.3.22.dist-info/entry_points.txt
archgw-0.3.22.dist-info/RECORD
